cherry/.gitignore
cherry/__init__.py
cherry/cherrypie.py
cherry/source/__init__.py
cherry/source/files.py
cherry/source/folders.py
cherry/source/try.py
cherry/source/virtual.py
cherry/source/utils/.env.txt
cherry/source/utils/.gitignore.txt
cherry/source/utils/__init__.py
cherry/source/utils/config.py.txt
cherry/source/utils/db.py.txt
cherry/source/utils/main.py.txt
cherry/source/utils/models.py.txt
cherry/source/utils/requirements.txt.txt
cherry/source/utils/route.py.txt
cherry/source/utils/schemas.py.txt
cherry/source/utils/script1.py.txt
cherry/source/utils/test_example.py.txt
cherry/source/utils/try2.py
cherry/source/utils/utils.py.txt
sour_cherry-1.0.12.dist-info/METADATA
sour_cherry-1.0.12.dist-info/WHEEL
sour_cherry-1.0.12.dist-info/entry_points.txt
sour_cherry-1.0.12.dist-info/licenses/LICENSE
sour_cherry-1.0.12.dist-info/RECORD
