Metadata-Version: 2.1
Name: sour-cherry
Version: 1.0.12
Summary: A CLI tool to build essentials for FastAPI development.
Project-URL: Homepage, https://github.com/CheruiyotLimo/project-cherry
Author-email: Yony Kibiwot <limzyon@gmail.com>
License-File: LICENSE
Classifier: Development Status :: 4 - Beta
Classifier: License :: OSI Approved :: MIT License
Classifier: Operating System :: OS Independent
Classifier: Programming Language :: Python :: 3
Requires-Python: >=3.8
Requires-Dist: click
